reporoulette/__init__.py
reporoulette/logging_config.py
reporoulette/py.typed
reporoulette/samplers/__init__.py
reporoulette/samplers/base.py
reporoulette/samplers/bigquery_sampler.py
reporoulette/samplers/bq_utils.py
reporoulette/samplers/gh_sampler.py
reporoulette/samplers/id_sampler.py
reporoulette/samplers/temporal_sampler.py
reporoulette-0.4.0.dist-info/WHEEL
reporoulette-0.4.0.dist-info/METADATA
reporoulette-0.4.0.dist-info/RECORD
