Metadata-Version: 2.3
Name: reporoulette
Version: 0.4.0
Summary: Random sampling of GitHub repositories using multiple methods
Keywords: github,repository,sampling,random,research,data-collection,bigquery,git
Author: Gaurav Sood
Author-email: Gaurav Sood <gsood07@example.com>
License: MIT License
Classifier: Development Status :: 4 - Beta
Classifier: Intended Audience :: Developers
Classifier: Intended Audience :: Science/Research
Classifier: License :: OSI Approved :: MIT License
Classifier: Operating System :: OS Independent
Classifier: Programming Language :: Python :: 3
Classifier: Programming Language :: Python :: 3.12
Classifier: Programming Language :: Python :: 3.13
Classifier: Programming Language :: Python :: 3.14
Classifier: Topic :: Software Development :: Libraries :: Python Modules
Classifier: Topic :: Software Development :: Version Control :: Git
Classifier: Topic :: Scientific/Engineering :: Information Analysis
Classifier: Typing :: Typed
Requires-Dist: requests>=2.25.0
Requires-Dist: google-cloud-bigquery>=2.0.0 ; extra == 'bigquery'
Requires-Dist: google-auth>=1.30.0 ; extra == 'bigquery'
Requires-Dist: pytest>=7.0.0 ; extra == 'dev'
Requires-Dist: pytest-cov>=3.0.0 ; extra == 'dev'
Requires-Dist: ruff>=0.8.0 ; extra == 'dev'
Requires-Dist: pre-commit>=3.0.0 ; extra == 'dev'
Requires-Dist: sphinx>=4.0.0 ; extra == 'docs'
Requires-Dist: furo>=2023.0.0 ; extra == 'docs'
Requires-Dist: myst-parser>=0.15.0 ; extra == 'docs'
Requires-Python: >=3.12
Project-URL: Bug Tracker, https://github.com/gojiplus/reporoulette/issues
Project-URL: Changelog, https://github.com/gojiplus/reporoulette/releases
Project-URL: Documentation, https://gojiplus.github.io/reporoulette/
Project-URL: Homepage, https://github.com/gojiplus/reporoulette
Project-URL: Repository, https://github.com/gojiplus/reporoulette
Provides-Extra: all
Provides-Extra: bigquery
Provides-Extra: dev
Provides-Extra: docs
